buf/validate/expression_pb2.py
buf/validate/expression_pb2_grpc.py
buf/validate/validate_pb2.py
buf/validate/validate_pb2_grpc.py
buf/validate/priv/private_pb2.py
buf/validate/priv/private_pb2_grpc.py
google/api/annotations_pb2.py
google/api/annotations_pb2_grpc.py
google/api/http_pb2.py
google/api/http_pb2_grpc.py
google/rpc/status_pb2.py
google/rpc/status_pb2_grpc.py
vald/v1/agent/core/agent_pb2.py
vald/v1/agent/core/agent_pb2_grpc.py
vald/v1/filter/egress/egress_filter_pb2.py
vald/v1/filter/egress/egress_filter_pb2_grpc.py
vald/v1/filter/ingress/ingress_filter_pb2.py
vald/v1/filter/ingress/ingress_filter_pb2_grpc.py
vald/v1/payload/payload_pb2.py
vald/v1/payload/payload_pb2_grpc.py
vald/v1/rpc/errdetails/error_details_pb2.py
vald/v1/rpc/errdetails/error_details_pb2_grpc.py
vald/v1/vald/filter_pb2.py
vald/v1/vald/filter_pb2_grpc.py
vald/v1/vald/flush_pb2.py
vald/v1/vald/flush_pb2_grpc.py
vald/v1/vald/index_pb2.py
vald/v1/vald/index_pb2_grpc.py
vald/v1/vald/insert_pb2.py
vald/v1/vald/insert_pb2_grpc.py
vald/v1/vald/object_pb2.py
vald/v1/vald/object_pb2_grpc.py
vald/v1/vald/remove_pb2.py
vald/v1/vald/remove_pb2_grpc.py
vald/v1/vald/search_pb2.py
vald/v1/vald/search_pb2_grpc.py
vald/v1/vald/update_pb2.py
vald/v1/vald/update_pb2_grpc.py
vald/v1/vald/upsert_pb2.py
vald/v1/vald/upsert_pb2_grpc.py
vald_client_python-1.7.17.dist-info/LICENSE
vald_client_python-1.7.17.dist-info/METADATA
vald_client_python-1.7.17.dist-info/WHEEL
vald_client_python-1.7.17.dist-info/top_level.txt
vald_client_python-1.7.17.dist-info/RECORD
