Metadata-Version: 2.1
Name: vald-client-python
Version: 1.7.17
Summary: a client library for Vald (https://github.com/vdaas/vald).
Home-page: https://github.com/vdaas/vald-client-python
Author: vald team
Author-email: vald@vdaas.org
License-File: LICENSE
Requires-Dist: protobuf
Requires-Dist: grpcio
Requires-Dist: googleapis-common-protos
